CREDITS
LICENSE
README.md
setup.cfg
setup.py
asyncorews/__init__.py
asyncorews/websocket.py
asyncorews.egg-info/PKG-INFO
asyncorews.egg-info/SOURCES.txt
asyncorews.egg-info/dependency_links.txt
asyncorews.egg-info/entry_points.txt
asyncorews.egg-info/not-zip-safe
asyncorews.egg-info/top_level.txt