Metadata-Version: 1.0
Name: asyncorews
Version: 0.1
Summary: Simple asyncore-based websocket server
Home-page: UNKNOWN
Author: Petri Savolainen
Author-email: petri.savolainen@koodaamo.fi
License: GPL
Keywords: websocket
Platform: UNKNOWN
